colibri_cli/__init__.py
colibri_cli/config.py
colibri_cli/main.py
colibri_cli/upload.py
colibri_cli-0.1.0.dist-info/METADATA
colibri_cli-0.1.0.dist-info/WHEEL
colibri_cli-0.1.0.dist-info/entry_points.txt
colibri_cli-0.1.0.dist-info/RECORD
