Metadata-Version: 2.4
Name: colibri-cli
Version: 0.1.0
Summary: CLI for uploading dbt artifacts to Colibri Pro
Author: Colibri Pro
License-Expression: MIT
Keywords: colibri,dbt,lineage
Classifier: Development Status :: 4 - Beta
Classifier: Programming Language :: Python :: 3
Classifier: Programming Language :: Python :: 3.9
Classifier: Programming Language :: Python :: 3.10
Classifier: Programming Language :: Python :: 3.11
Classifier: Programming Language :: Python :: 3.12
Requires-Python: >=3.9
Requires-Dist: click>=8.1.0
Requires-Dist: requests>=2.31.0
Requires-Dist: rich>=13.0.0
Provides-Extra: dev
Requires-Dist: pytest-cov>=4.0.0; extra == 'dev'
Requires-Dist: pytest>=7.0.0; extra == 'dev'
Requires-Dist: ruff>=0.1.0; extra == 'dev'
